fetch_content_providers_and_resolvers/LICENSE
fetch_content_providers_and_resolvers/README.MD
fetch_content_providers_and_resolvers/__init__.py
fetch_content_providers_and_resolvers/requirements.txt
fetch_content_providers_and_resolvers/thirdparty.json
fetch_content_providers_and_resolvers-0.10.dist-info/LICENSE.rst
fetch_content_providers_and_resolvers-0.10.dist-info/METADATA
fetch_content_providers_and_resolvers-0.10.dist-info/WHEEL
fetch_content_providers_and_resolvers-0.10.dist-info/top_level.txt
fetch_content_providers_and_resolvers-0.10.dist-info/RECORD
