Metadata-Version: 2.1
Name: fetch-content-providers-and-resolvers
Version: 0.10
Summary: Finds content providers/resolvers on Android devices 
Home-page: https://github.com/hansalemaos/fetch_content_providers_and_resolvers
Author: Johannes Fischer
Author-email: <aulasparticularesdealemaosp@gmail.com>
License: MIT
Keywords: settings,adb,pandas,DataFrame,content,android,providers,resolvers
Classifier: Development Status :: 4 - Beta
Classifier: Programming Language :: Python :: 3 :: Only
Classifier: Programming Language :: Python :: 3.9
Classifier: Topic :: Scientific/Engineering :: Visualization
Classifier: Topic :: Software Development :: Libraries :: Python Modules
Classifier: Topic :: Text Editors :: Text Processing
Classifier: Topic :: Text Processing :: General
Classifier: Topic :: Text Processing :: Indexing
Classifier: Topic :: Text Processing :: Filters
Classifier: Topic :: Utilities
License-File: LICENSE.rst
Requires-Dist: a-pandas-ex-adb-to-df
Requires-Dist: a-pandas-ex-plode-tool
Requires-Dist: cprinter
Requires-Dist: flatten-everything
Requires-Dist: list-all-files-recursively
Requires-Dist: pandas
Requires-Dist: PyRipGrep
